[
    {
        "key": "dbln",
        "value": "%7B%22100080456630885%22%3A%22UIV0bnWL%22%2C%22100015721440033%22%3A%22OpVm3zc9%22%7D",
        "domain": "facebook.com",
        "path": "/login/device-based/",
        "hostOnly": false,
        "creation": "2024-10-19T09:34:45.608Z",
        "lastAccessed": "2024-10-19T09:34:45.609Z"
    },
    {
        "key": "sb",
        "value": "5S-MZneDGKxtrhLR_pOYR9Ks",
        "domain": "facebook.com",
        "path": "/",
        "hostOnly": false,
        "creation": "2024-10-19T09:34:45.609Z",
        "lastAccessed": "2024-10-19T09:34:45.609Z"
    },
    {
        "key": "ps_l",
        "value": "1",
        "domain": "facebook.com",
        "path": "/",
        "hostOnly": false,
        "creation": "2024-10-19T09:34:45.609Z",
        "lastAccessed": "2024-10-19T09:34:45.609Z"
    },
    {
        "key": "ps_n",
        "value": "1",
        "domain": "facebook.com",
        "path": "/",
        "hostOnly": false,
        "creation": "2024-10-19T09:34:45.609Z",
        "lastAccessed": "2024-10-19T09:34:45.609Z"
    },
    {
        "key": "oo",
        "value": "v1",
        "domain": "facebook.com",
        "path": "/",
        "hostOnly": false,
        "creation": "2024-10-19T09:34:45.609Z",
        "lastAccessed": "2024-10-19T09:34:45.609Z"
    },
    {
        "key": "vpd",
        "value": "v1%3B984x480x1.8012806177139282",
        "domain": "facebook.com",
        "path": "/",
        "hostOnly": false,
        "creation": "2024-10-19T09:34:45.609Z",
        "lastAccessed": "2024-10-19T09:34:45.609Z"
    },
    {
        "key": "locale",
        "value": "en_GB",
        "domain": "facebook.com",
        "path": "/",
        "hostOnly": false,
        "creation": "2024-10-19T09:34:45.609Z",
        "lastAccessed": "2024-10-19T09:34:45.609Z"
    },
    {
        "key": "wl_cbv",
        "value": "v2%3Bclient_version%3A2645%3Btimestamp%3A1728735802",
        "domain": "facebook.com",
        "path": "/",
        "hostOnly": false,
        "creation": "2024-10-19T09:34:45.609Z",
        "lastAccessed": "2024-10-19T09:34:45.609Z"
    },
    {
        "key": "dpr",
        "value": "1.9804123640060425",
        "domain": "facebook.com",
        "path": "/",
        "hostOnly": false,
        "creation": "2024-10-19T09:34:45.609Z",
        "lastAccessed": "2024-10-19T09:34:45.609Z"
    },
    {
        "key": "datr",
        "value": "dekNZ2ENyf5a8ydAa7S9rtD4",
        "domain": "facebook.com",
        "path": "/",
        "hostOnly": false,
        "creation": "2024-10-19T09:34:45.609Z",
        "lastAccessed": "2024-10-19T09:34:45.609Z"
    },
    {
        "key": "c_user",
        "value": "61557874015534",
        "domain": "facebook.com",
        "path": "/",
        "hostOnly": false,
        "creation": "2024-10-19T09:34:45.609Z",
        "lastAccessed": "2024-10-19T09:34:45.609Z"
    },
    {
        "key": "xs",
        "value": "19%3Axr3BuXRe6v_M9Q%3A2%3A1729330429%3A-1%3A10313",
        "domain": "facebook.com",
        "path": "/",
        "hostOnly": false,
        "creation": "2024-10-19T09:34:45.609Z",
        "lastAccessed": "2024-10-19T09:34:45.609Z"
    },
    {
        "key": "fr",
        "value": "1AxG2MKSrW1yu7aRE.AWUg86RWBrNn2mMtLO5uCWiNxi0.BnE3e1..AAA.0.0.BnE3z-.AWWrcKTyl6o",
        "domain": "facebook.com",
        "path": "/",
        "hostOnly": false,
        "creation": "2024-10-19T09:34:45.609Z",
        "lastAccessed": "2024-10-19T09:34:45.609Z"
    },
    {
        "key": "presence",
        "value": "C%7B%22t3%22%3A%5B%5D%2C%22utc3%22%3A1729330441075%2C%22v%22%3A1%7D",
        "domain": "facebook.com",
        "path": "/",
        "hostOnly": false,
        "creation": "2024-10-19T09:34:45.609Z",
        "lastAccessed": "2024-10-19T09:34:45.609Z"
    },
    {
        "key": "wd",
        "value": "1113x2283",
        "domain": "facebook.com",
        "path": "/",
        "hostOnly": false,
        "creation": "2024-10-19T09:34:45.609Z",
        "lastAccessed": "2024-10-19T09:34:45.609Z"
    }
]
